Metadata-Version: 2.4
Name: simple-report
Version: 0.0.23
Summary: Simple HTML report generation using Python
Home-page: https://github.com/dougsgrott/simple-report
Author: Douglas Sgrott
Author-email: doug.sgrott@gmail.com
License: MIT
Project-URL: bug tracker, https://github.com/alod83/package_template/issues
Classifier: Programming Language :: Python :: 3
Classifier: License :: OSI Approved :: MIT License
Classifier: Operating System :: OS Independent
Requires-Python: >=3.6
License-File: LICENSE
Provides-Extra: notebook
Requires-Dist: jupyter-client>=5.3.4; extra == "notebook"
Requires-Dist: jupyter-core>=4.6.3; extra == "notebook"
Requires-Dist: ipywidgets>=7.5.1; extra == "notebook"
Dynamic: author
Dynamic: author-email
Dynamic: home-page
Dynamic: license
Dynamic: license-file
Dynamic: provides-extra
Dynamic: requires-python
Dynamic: summary
